strptime.py
strptime_cli-0.4.0.dist-info/METADATA
strptime_cli-0.4.0.dist-info/WHEEL
strptime_cli-0.4.0.dist-info/entry_points.txt
strptime_cli-0.4.0.dist-info/RECORD
