Metadata-Version: 2.3
Name: strptime-cli
Version: 0.4.0
Project-URL: Documentation, https://github.com/treyhunner/strptime-cli#readme
Project-URL: Issues, https://github.com/treyhunner/strptime-cli/issues
Project-URL: Source, https://github.com/treyhunner/strptime-cli
Author: Trey Hunner
License: MIT
Classifier: Development Status :: 2 - Pre-Alpha
Classifier: Programming Language :: Python
Classifier: Programming Language :: Python :: 3.9
Classifier: Programming Language :: Python :: 3.10
Classifier: Programming Language :: Python :: 3.11
Classifier: Programming Language :: Python :: 3.12
Classifier: Programming Language :: Python :: 3.13
Classifier: Programming Language :: Python :: Implementation :: CPython
Classifier: Programming Language :: Python :: Implementation :: PyPy
Requires-Python: >=3.9
Requires-Dist: darkdetect
Requires-Dist: platformdirs
Requires-Dist: pyperclip
Requires-Dist: textual
